odoo/addons/intrastat_delivery/README.rst
odoo/addons/intrastat_delivery/__init__.py
odoo/addons/intrastat_delivery/__manifest__.py
odoo/addons/intrastat_delivery/i18n/es.po
odoo/addons/intrastat_delivery/i18n/intrastat_delivery.pot
odoo/addons/intrastat_delivery/i18n/it.po
odoo/addons/intrastat_delivery/models/__init__.py
odoo/addons/intrastat_delivery/models/delivery_carrier.py
odoo/addons/intrastat_delivery/models/sale_order.py
odoo/addons/intrastat_delivery/readme/CONFIGURE.rst
odoo/addons/intrastat_delivery/readme/CONTRIBUTORS.rst
odoo/addons/intrastat_delivery/readme/CREDITS.rst
odoo/addons/intrastat_delivery/readme/DESCRIPTION.rst
odoo/addons/intrastat_delivery/readme/DEVELOP.rst
odoo/addons/intrastat_delivery/readme/HISTORY.rst
odoo/addons/intrastat_delivery/readme/INSTALL.rst
odoo/addons/intrastat_delivery/readme/ROADMAP.rst
odoo/addons/intrastat_delivery/readme/USAGE.rst
odoo/addons/intrastat_delivery/static/description/icon.png
odoo/addons/intrastat_delivery/static/description/index.html
odoo/addons/intrastat_delivery/tests/__init__.py
odoo/addons/intrastat_delivery/tests/test_intrastat_delivery.py
odoo/addons/intrastat_delivery/views/delivery_carrier_view.xml
odoo_addon_intrastat_delivery-16.0.1.0.0.5.dist-info/METADATA
odoo_addon_intrastat_delivery-16.0.1.0.0.5.dist-info/WHEEL
odoo_addon_intrastat_delivery-16.0.1.0.0.5.dist-info/top_level.txt
odoo_addon_intrastat_delivery-16.0.1.0.0.5.dist-info/RECORD
