Metadata-Version: 2.1
Name: odoo-addon-intrastat_delivery
Version: 16.0.1.0.0.5
Summary: Propagates the value of the incoterm fields from the order shipping method to the invoices
Home-page: https://github.com/OCA/intrastat-extrastat
Author: FactorLibre, Odoo Community Association (OCA)
Author-email: support@odoo-community.org
License: AGPL-3
Classifier: Programming Language :: Python
Classifier: Framework :: Odoo
Classifier: Framework :: Odoo :: 16.0
Classifier: License :: OSI Approved :: GNU Affero General Public License v3
Requires-Python: >=3.10
Requires-Dist: odoo-addon-intrastat-product <16.1dev,>=16.0dev
Requires-Dist: odoo <16.1dev,>=16.0a
